MANIFEST.in
README.rst
setup.py
django_icons_web_control.egg-info/PKG-INFO
django_icons_web_control.egg-info/SOURCES.txt
django_icons_web_control.egg-info/dependency_links.txt
django_icons_web_control.egg-info/requires.txt
django_icons_web_control.egg-info/top_level.txt
icons_web_control/__init__.py
icons_web_control/models.py
icons_web_control/static/icons/.noremove
icons_web_control/static/icons/web_control/license.txt
icons_web_control/static/icons/web_control/16x16/black_chartlink.gif
icons_web_control/static/icons/web_control/16x16/black_chartlink.png
icons_web_control/static/icons/web_control/16x16/black_config.gif
icons_web_control/static/icons/web_control/16x16/black_config.png
icons_web_control/static/icons/web_control/16x16/black_delete.gif
icons_web_control/static/icons/web_control/16x16/black_delete.png
icons_web_control/static/icons/web_control/16x16/black_down.gif
icons_web_control/static/icons/web_control/16x16/black_down.png
icons_web_control/static/icons/web_control/16x16/black_edit.gif
icons_web_control/static/icons/web_control/16x16/black_edit.png
icons_web_control/static/icons/web_control/16x16/black_gallerylink.gif
icons_web_control/static/icons/web_control/16x16/black_gallerylink.png
icons_web_control/static/icons/web_control/16x16/black_imagelink.gif
icons_web_control/static/icons/web_control/16x16/black_imagelink.png
icons_web_control/static/icons/web_control/16x16/black_info.gif
icons_web_control/static/icons/web_control/16x16/black_info.png
icons_web_control/static/icons/web_control/16x16/black_print.gif
icons_web_control/static/icons/web_control/16x16/black_print.png
icons_web_control/static/icons/web_control/16x16/black_up.gif
icons_web_control/static/icons/web_control/16x16/black_up.png
icons_web_control/static/icons/web_control/16x16/black_view.gif
icons_web_control/static/icons/web_control/16x16/black_view.png
icons_web_control/static/icons/web_control/16x16/blue_chartlink.gif
icons_web_control/static/icons/web_control/16x16/blue_chartlink.png
icons_web_control/static/icons/web_control/16x16/blue_config.gif
icons_web_control/static/icons/web_control/16x16/blue_config.png
icons_web_control/static/icons/web_control/16x16/blue_delete.gif
